[
  {
    "consumableGroup": 1,
    "itemCode": 301205,
    "amount": 2
  },
  {
    "consumableGroup": 1,
    "itemCode": 301209,
    "amount": 2
  },
  {
    "consumableGroup": 1,
    "itemCode": 301304,
    "amount": 1
  },
  {
    "consumableGroup": 1,
    "itemCode": 301303,
    "amount": 1
  },
  {
    "consumableGroup": 2,
    "itemCode": 301205,
    "amount": 4
  },
  {
    "consumableGroup": 2,
    "itemCode": 301209,
    "amount": 4
  },
  {
    "consumableGroup": 2,
    "itemCode": 301304,
    "amount": 2
  },
  {
    "consumableGroup": 2,
    "itemCode": 301303,
    "amount": 2
  },
  {
    "consumableGroup": 3,
    "itemCode": 301401,
    "amount": 2
  },
  {
    "consumableGroup": 3,
    "itemCode": 301329,
    "amount": 2
  },
  {
    "consumableGroup": 1,
    "itemCode": 502207,
    "amount": 1
  },
  {
    "consumableGroup": 2,
    "itemCode": 502207,
    "amount": 2
  },
  {
    "consumableGroup": 3,
    "itemCode": 502403,
    "amount": 2
  },
  {
    "consumableGroup": 2,
    "itemCode": 301401,
    "amount": 1
  },
  {
    "consumableGroup": 2,
    "itemCode": 301329,
    "amount": 1
  },
  {
    "consumableGroup": 3,
    "itemCode": 301304,
    "amount": 4
  },
  {
    "consumableGroup": 3,
    "itemCode": 301303,
    "amount": 4
  }
]