{
  "Achievement": 25497290,
  "Achievements": 2670826207,
  "ActionCost": 3476273430,
  "ActionCost_Light": 2351618591,
  "Area": 204561368,
  "AreaAttributes": 2139000326,
  "AreaAttributes_V2": 973206913,
  "AreaSound": 730081893,
  "AttendRewardList": 1186740627,
  "Attendance": 3647620956,
  "AutoExchangeToken": 486208167,
  "BattlePassMission": 821923111,
  "BattlePassReward": 1193533189,
  "BattlePassRewardItem": 1532063748,
  "BattleZoneReward": 267815228,
  "BattlefieldArea": 637359149,
  "Blueprint": 3624738590,
  "Booster": 67349930,
  "BotAiModel": 1889052284,
  "BotCraft": 1936108714,
  "BotMastery": 115482338,
  "BotNickName": 3277384830,
  "BotSkillBuild": 1316321053,
  "BulletCapacity": 2845323702,
  "BulletCapacity_Light": 1060615826,
  "Character": 73988383,
  "CharacterAttributes": 2173108006,
  "CharacterExp": 2009138779,
  "CharacterLevelUpStat": 1514895594,
  "CharacterMastery": 3731098809,
  "CharacterMastery의 사본": 1185266985,
  "CharacterModeModifier": 1229115576,
  "CharacterModeModifier_Light": 3169709200,
  "CharacterSkillVideos": 2536553328,
  "CharacterSkin": 3565630194,
  "CharacterState": 2077518650,
  "CharacterStateGroup": 1024986286,
  "CharacterVoice": 2056197974,
  "CharacterVoiceRandomCount": 4018476585,
  "Character_Light": 4237188792,
  "CobaltWall": 701538023,
  "Collectible": 3456809532,
  "Collection": 1600870568,
  "CollectionList": 2388152176,
  "ContentOpen": 408816350,
  "ControlTypeUse": 1705422735,
  "CountryGroup": 1706934491,
  "CriticalChance": 1584487193,
  "CrowdControlData": 603236780,
  "DeployingPoint": 3529425588,
  "DiceConsumableSheet": 342876939,
  "DiceItemSheet": 371136991,
  "DropGroup": 2495382824,
  "DropGroup_Light": 1547786096,
  "DropGroup의 사본": 1571124533,
  "DyingConditionSkill": 130946931,
  "EffectAndSound": 2041257870,
  "EliteMonsterSpawn": 2985526518,
  "Emblem": 1042396169,
  "Emotion": 2934069572,
  "EntryCostRP": 2896867392,
  "EventPassMission": 980608221,
  "EventRewardUser": 3276512689,
  "FeverTimeData": 4081777300,
  "FeverTimeReward": 2389677926,
  "FootStep": 3908459787,
  "GadgetObject": 1184794176,
  "GainExp": 3026996341,
  "GainScore": 514675210,
  "GameBattleStar": 282895696,
  "GameConstant": 297003148,
  "GameRankExp": 2576240728,
  "GameTip": 3037330213,
  "GameTipCategory": 3316653107,
  "GameTip_V2": 2757094063,
  "Goods": 506772945,
  "GoodsGroup": 4254405386,
  "HealPack": 936666491,
  "HookLineProjectile": 2992236781,
  "HowToFindItem": 1670453132,
  "HyperSynthesisDevice": 1513251990,
  "InGameOperator": 2860287589,
  "InfusionProduct": 2593344148,
  "Installation": 1106486423,
  "InstallationMovable": 1916361734,
  "ItemAcquireInfo": 2637509891,
  "ItemArmor": 125596919,
  "ItemConsumable": 890247888,
  "ItemConsumable_Light": 1506254796,
  "ItemMisc": 2239038469,
  "ItemMisc_Light": 3344340985,
  "ItemSearchOption": 4067378189,
  "ItemSearchOptionV2": 2277319241,
  "ItemSkill": 4180494603,
  "ItemSkillGroup": 1495604488,
  "ItemSkillLinker": 1303599207,
  "ItemSpawn": 4292705862,
  "ItemSpecial": 194190553,
  "ItemSpecial_Light": 83721643,
  "ItemWeapon": 1006525806,
  "KeyText": 3541518974,
  "Level": 1502997333,
  "LimitedDropGroup": 2389324849,
  "LoadingTip": 2037625861,
  "LowestRankAdjust": 4284431522,
  "MasteryExp": 3651173253,
  "MasteryLevel": 463638786,
  "MasteryStat": 1668326376,
  "MatchingQueueTier": 3497714049,
  "Mission": 666589714,
  "ModRestrictedArea": 3169485016,
  "Monster": 2573943108,
  "MonsterDropGroup": 2659608545,
  "MonsterGroup": 52593416,
  "MonsterLevelUpStat": 1755076577,
  "MonsterLevelUpStat_Light": 4129143757,
  "MonsterSpawnLevel": 2244026137,
  "MonsterSpawnLevel_Light": 4084635151,
  "MonsterVFShard_Light": 152939422,
  "Monster_Light": 2171790617,
  "MutantMonsterSpawn": 4224992079,
  "NaviCollectAndHunt": 317572060,
  "NearByArea": 685603230,
  "Noise": 1881317192,
  "ObjectSkin": 4148055125,
  "PersonalShop": 2727323466,
  "PersonalShopConstant": 3595244541,
  "Phase": 3320417305,
  "PraiseHonorLevel": 2480108335,
  "PreMadeTeamTierRestrict": 686990809,
  "ProductAsset": 535659512,
  "ProductCharacter": 1501187027,
  "ProductInstant": 1334912569,
  "ProjectileDeflectorSetting": 3616550141,
  "ProjectileSetting": 2750199026,
  "ProjectileSetting_Light": 3586084906,
  "RandomBox": 642552186,
  "RandomBoxGroup": 3596543450,
  "RandomBoxItem": 1057225716,
  "RandomBoxItems": 46545389,
  "RandomBoxSelector": 2894426074,
  "RandomEquipment": 3985691423,
  "RankAndKillRP": 3627571127,
  "RecommendedArea": 1604025550,
  "RecommendedItemList": 567504821,
  "RecommendedList": 3617361338,
  "ReplicaPoint": 3853307756,
  "RestrictedArea": 1337300115,
  "RestrictedArea_V2": 94957898,
  "Reward": 2255572208,
  "RewardItem": 3244457258,
  "RewindProjectile": 1221257027,
  "Season": 1407972526,
  "SeasonOutPlayers": 3141375834,
  "SecurityConsolEvent": 1584900824,
  "ServerRegion": 1260054034,
  "ShopProduct": 3008337146,
  "ShopProductItem": 2459668836,
  "ShopProductSeq": 4029120817,
  "Skill": 1716910011,
  "SkillEvolution": 3686397505,
  "SkillEvolutionGroup": 3902923477,
  "SkillEvolutionPoint": 1229268597,
  "SkillExtension": 1199810687,
  "SkillGroup": 4006426390,
  "Skill_Indicator": 638499235,
  "SoundGroup": 179238568,
  "StartItem": 2813809412,
  "StateTypeData": 1746280872,
  "SummonObject": 3196595960,
  "SummonObjectGroup": 372067080,
  "SummonObjectStat": 3285185401,
  "SummonObjectStat_Light": 132738809,
  "SummonObject_Light": 2181980949,
  "SupportPack": 3429893022,
  "TacticalSkillSet": 3251871595,
  "TacticalSkillSetGroup": 2787816076,
  "TimeOfDay": 650137010,
  "TokenExchange": 1376842864,
  "TokenExchangeItem": 1503506453,
  "TouringObjectData": 739023559,
  "Trait": 105882070,
  "TransferConsole": 524451152,
  "Turbine": 478925357,
  "TutorialReward": 1872389453,
  "VFCredit": 4049916366,
  "VFCredit_S5": 1119116422,
  "WeaponAnimatorLayers": 2403011431,
  "WeaponMount": 900741555,
  "WeaponRoute": 2756065572,
  "WeaponTypeInfo": 1411360712,
  "Weather": 547255317
}