[
  {
    "code": 502101,
    "name": "감시카메라",
    "modeType": 0,
    "itemType": "Special",
    "specialItemType": "Summon",
    "itemGrade": "Common",
    "isCompletedItem": false,
    "markingType": "None",
    "craftAnimTrigger": "craftMetal",
    "stackable": 5,
    "initialCount": 1,
    "itemUsableType": "ALL",
    "itemUsableValueList": 0,
    "exclusiveProducer": 0,
    "canNotBeTakeItemFromCorpse": false,
    "manufacturableType": 1,
    "makeMaterial1": 0,
    "makeMaterial2": 0,
    "consumeCount": 1,
    "summonCode": 1,
    "restoreItemWhenResurrected": true
  },
  {
    "code": 502102,
    "name": "올가미",
    "modeType": 0,
    "itemType": "Special",
    "specialItemType": "Summon",
    "itemGrade": "Common",
    "isCompletedItem": false,
    "markingType": "None",
    "craftAnimTrigger": "craftMetal",
    "stackable": 5,
    "initialCount": 2,
    "itemUsableType": "ALL",
    "itemUsableValueList": 0,
    "exclusiveProducer": 0,
    "canNotBeTakeItemFromCorpse": false,
    "manufacturableType": 1,
    "makeMaterial1": 0,
    "makeMaterial2": 0,
    "consumeCount": 1,
    "summonCode": 2,
    "restoreItemWhenResurrected": true
  },
  {
    "code": 502103,
    "name": "쥐덫",
    "modeType": 0,
    "itemType": "Special",
    "specialItemType": "Summon",
    "itemGrade": "Common",
    "isCompletedItem": false,
    "markingType": "None",
    "craftAnimTrigger": "craftMetal",
    "stackable": 5,
    "initialCount": 2,
    "itemUsableType": "ALL",
    "itemUsableValueList": 0,
    "exclusiveProducer": 0,
    "canNotBeTakeItemFromCorpse": false,
    "manufacturableType": 1,
    "makeMaterial1": 0,
    "makeMaterial2": 0,
    "consumeCount": 1,
    "summonCode": 3,
    "restoreItemWhenResurrected": true
  },
  {
    "code": 502201,
    "name": "가시발판",
    "modeType": 0,
    "itemType": "Special",
    "specialItemType": "Summon",
    "itemGrade": "Uncommon",
    "isCompletedItem": false,
    "markingType": "None",
    "craftAnimTrigger": "craftMetal",
    "stackable": 5,
    "initialCount": 2,
    "itemUsableType": "ALL",
    "itemUsableValueList": 0,
    "exclusiveProducer": 0,
    "canNotBeTakeItemFromCorpse": false,
    "manufacturableType": 0,
    "makeMaterial1": 502103,
    "makeMaterial2": 401101,
    "consumeCount": 1,
    "summonCode": 5,
    "restoreItemWhenResurrected": true
  },
  {
    "code": 502202,
    "name": "개량형쥐덫",
    "modeType": 0,
    "itemType": "Special",
    "specialItemType": "Summon",
    "itemGrade": "Uncommon",
    "isCompletedItem": false,
    "markingType": "None",
    "craftAnimTrigger": "craftMetal",
    "stackable": 5,
    "initialCount": 2,
    "itemUsableType": "ALL",
    "itemUsableValueList": 0,
    "exclusiveProducer": 0,
    "canNotBeTakeItemFromCorpse": false,
    "manufacturableType": 0,
    "makeMaterial1": 502103,
    "makeMaterial2": 401118,
    "consumeCount": 1,
    "summonCode": 6,
    "restoreItemWhenResurrected": true
  },
  {
    "code": 502203,
    "name": "다이너마이트",
    "modeType": 0,
    "itemType": "Special",
    "specialItemType": "Summon",
    "itemGrade": "Uncommon",
    "isCompletedItem": false,
    "markingType": "None",
    "craftAnimTrigger": "craftMetal",
    "stackable": 5,
    "initialCount": 1,
    "itemUsableType": "ALL",
    "itemUsableValueList": 0,
    "exclusiveProducer": 0,
    "canNotBeTakeItemFromCorpse": false,
    "manufacturableType": 0,
    "makeMaterial1": 502104,
    "makeMaterial2": 401121,
    "consumeCount": 1,
    "summonCode": 7,
    "restoreItemWhenResurrected": true
  },
  {
    "code": 502204,
    "name": "대나무트랩",
    "modeType": 0,
    "itemType": "Special",
    "specialItemType": "Summon",
    "itemGrade": "Uncommon",
    "isCompletedItem": false,
    "markingType": "None",
    "craftAnimTrigger": "craftMetal",
    "stackable": 5,
    "initialCount": 2,
    "itemUsableType": "ALL",
    "itemUsableValueList": 0,
    "exclusiveProducer": 0,
    "canNotBeTakeItemFromCorpse": false,
    "manufacturableType": 0,
    "makeMaterial1": 502102,
    "makeMaterial2": 108103,
    "consumeCount": 1,
    "summonCode": 8,
    "restoreItemWhenResurrected": true
  },
  {
    "code": 502205,
    "name": "부비트랩",
    "modeType": 0,
    "itemType": "Special",
    "specialItemType": "Summon",
    "itemGrade": "Uncommon",
    "isCompletedItem": false,
    "markingType": "None",
    "craftAnimTrigger": "craftMetal",
    "stackable": 5,
    "initialCount": 2,
    "itemUsableType": "ALL",
    "itemUsableValueList": 0,
    "exclusiveProducer": 0,
    "canNotBeTakeItemFromCorpse": false,
    "manufacturableType": 0,
    "makeMaterial1": 502102,
    "makeMaterial2": 401116,
    "consumeCount": 1,
    "summonCode": 9,
    "restoreItemWhenResurrected": true
  },
  {
    "code": 502206,
    "name": "소란발생기",
    "modeType": 0,
    "itemType": "Special",
    "specialItemType": "Summon",
    "itemGrade": "Uncommon",
    "isCompletedItem": true,
    "markingType": "None",
    "craftAnimTrigger": "craftMetal",
    "stackable": 5,
    "initialCount": 2,
    "itemUsableType": "ALL",
    "itemUsableValueList": 0,
    "exclusiveProducer": 0,
    "canNotBeTakeItemFromCorpse": false,
    "manufacturableType": 0,
    "makeMaterial1": 401120,
    "makeMaterial2": 112103,
    "consumeCount": 1,
    "summonCode": 26,
    "restoreItemWhenResurrected": true
  },
  {
    "code": 502207,
    "name": "망원카메라",
    "modeType": 0,
    "itemType": "Special",
    "specialItemType": "Summon",
    "itemGrade": "Uncommon",
    "isCompletedItem": true,
    "markingType": "None",
    "craftAnimTrigger": "craftMetal",
    "stackable": 6,
    "initialCount": 2,
    "itemUsableType": "ALL",
    "itemUsableValueList": 0,
    "exclusiveProducer": 0,
    "canNotBeTakeItemFromCorpse": false,
    "manufacturableType": 0,
    "makeMaterial1": 502101,
    "makeMaterial2": 205110,
    "consumeCount": 1,
    "summonCode": 27,
    "restoreItemWhenResurrected": true
  },
  {
    "code": 502208,
    "name": "정찰드론",
    "modeType": 0,
    "itemType": "Special",
    "specialItemType": "Summon",
    "itemGrade": "Uncommon",
    "isCompletedItem": false,
    "markingType": "None",
    "craftAnimTrigger": "craftMetal",
    "stackable": 6,
    "initialCount": 2,
    "itemUsableType": "ALL",
    "itemUsableValueList": 0,
    "exclusiveProducer": 0,
    "canNotBeTakeItemFromCorpse": false,
    "manufacturableType": 0,
    "makeMaterial1": 502101,
    "makeMaterial2": 401121,
    "consumeCount": 1,
    "summonCode": 28,
    "restoreItemWhenResurrected": true
  },
  {
    "code": 502209,
    "name": "위장카메라",
    "modeType": 0,
    "itemType": "Special",
    "specialItemType": "Summon",
    "itemGrade": "Uncommon",
    "isCompletedItem": true,
    "markingType": "None",
    "craftAnimTrigger": "craftMetal",
    "stackable": 6,
    "initialCount": 2,
    "itemUsableType": "ALL",
    "itemUsableValueList": 0,
    "exclusiveProducer": "34, 57",
    "canNotBeTakeItemFromCorpse": false,
    "manufacturableType": 0,
    "makeMaterial1": 502101,
    "makeMaterial2": 108101,
    "consumeCount": 1,
    "summonCode": 1151,
    "restoreItemWhenResurrected": true
  },
  {
    "code": 502303,
    "name": "정글기요틴",
    "modeType": 0,
    "itemType": "Special",
    "specialItemType": "Summon",
    "itemGrade": "Uncommon",
    "isCompletedItem": false,
    "markingType": "None",
    "craftAnimTrigger": "craftMetal",
    "stackable": 5,
    "initialCount": 1,
    "itemUsableType": "ALL",
    "itemUsableValueList": 0,
    "exclusiveProducer": 0,
    "canNotBeTakeItemFromCorpse": false,
    "manufacturableType": 0,
    "makeMaterial1": 502103,
    "makeMaterial2": 102101,
    "consumeCount": 1,
    "summonCode": 12,
    "restoreItemWhenResurrected": true
  },
  {
    "code": 502304,
    "name": "지뢰",
    "modeType": 0,
    "itemType": "Special",
    "specialItemType": "Summon",
    "itemGrade": "Rare",
    "isCompletedItem": false,
    "markingType": "None",
    "craftAnimTrigger": "craftMetal",
    "stackable": 5,
    "initialCount": 2,
    "itemUsableType": "ALL",
    "itemUsableValueList": 0,
    "exclusiveProducer": 0,
    "canNotBeTakeItemFromCorpse": false,
    "manufacturableType": 0,
    "makeMaterial1": 502205,
    "makeMaterial2": 401121,
    "consumeCount": 1,
    "summonCode": 13,
    "restoreItemWhenResurrected": true
  },
  {
    "code": 502305,
    "name": "펜듈럼도끼",
    "modeType": 0,
    "itemType": "Special",
    "specialItemType": "Summon",
    "itemGrade": "Rare",
    "isCompletedItem": false,
    "markingType": "None",
    "craftAnimTrigger": "craftMetal",
    "stackable": 5,
    "initialCount": 2,
    "itemUsableType": "ALL",
    "itemUsableValueList": 0,
    "exclusiveProducer": 0,
    "canNotBeTakeItemFromCorpse": false,
    "manufacturableType": 0,
    "makeMaterial1": 502204,
    "makeMaterial2": 105103,
    "consumeCount": 1,
    "summonCode": 14,
    "restoreItemWhenResurrected": true
  },
  {
    "code": 502306,
    "name": "폭발트랩",
    "modeType": 0,
    "itemType": "Special",
    "specialItemType": "Summon",
    "itemGrade": "Uncommon",
    "isCompletedItem": false,
    "markingType": "None",
    "craftAnimTrigger": "craftMetal",
    "stackable": 5,
    "initialCount": 1,
    "itemUsableType": "ALL",
    "itemUsableValueList": 0,
    "exclusiveProducer": 0,
    "canNotBeTakeItemFromCorpse": false,
    "manufacturableType": 0,
    "makeMaterial1": 502103,
    "makeMaterial2": 401121,
    "consumeCount": 1,
    "summonCode": 15,
    "restoreItemWhenResurrected": true
  },
  {
    "code": 502307,
    "name": "RDX",
    "modeType": 0,
    "itemType": "Special",
    "specialItemType": "Summon",
    "itemGrade": "Rare",
    "isCompletedItem": false,
    "markingType": "None",
    "craftAnimTrigger": "craftMetal",
    "stackable": 5,
    "initialCount": 1,
    "itemUsableType": "ALL",
    "itemUsableValueList": 0,
    "exclusiveProducer": 0,
    "canNotBeTakeItemFromCorpse": false,
    "manufacturableType": 0,
    "makeMaterial1": 502203,
    "makeMaterial2": 401106,
    "consumeCount": 1,
    "summonCode": 16,
    "restoreItemWhenResurrected": true
  },
  {
    "code": 502308,
    "name": "EMP드론",
    "modeType": 0,
    "itemType": "Special",
    "specialItemType": "Summon",
    "itemGrade": "Rare",
    "isCompletedItem": true,
    "markingType": "None",
    "craftAnimTrigger": "craftMetal",
    "stackable": 6,
    "initialCount": 1,
    "itemUsableType": "ALL",
    "itemUsableValueList": 0,
    "exclusiveProducer": 0,
    "canNotBeTakeItemFromCorpse": false,
    "manufacturableType": 0,
    "makeMaterial1": 502208,
    "makeMaterial2": 401110,
    "consumeCount": 1,
    "summonCode": 29,
    "restoreItemWhenResurrected": true
  },
  {
    "code": 502401,
    "name": "미스릴실",
    "modeType": 0,
    "itemType": "Special",
    "specialItemType": "Summon",
    "itemGrade": "Epic",
    "isCompletedItem": true,
    "markingType": "None",
    "craftAnimTrigger": "craftMetal",
    "stackable": 5,
    "initialCount": 2,
    "itemUsableType": "ALL",
    "itemUsableValueList": 0,
    "exclusiveProducer": 0,
    "canNotBeTakeItemFromCorpse": false,
    "manufacturableType": 0,
    "makeMaterial1": 401304,
    "makeMaterial2": 502104,
    "consumeCount": 1,
    "summonCode": 17,
    "restoreItemWhenResurrected": true
  },
  {
    "code": 502402,
    "name": "폭뢰침",
    "modeType": 0,
    "itemType": "Special",
    "specialItemType": "Summon",
    "itemGrade": "Epic",
    "isCompletedItem": true,
    "markingType": "None",
    "craftAnimTrigger": "craftMetal",
    "stackable": 5,
    "initialCount": 2,
    "itemUsableType": "ALL",
    "itemUsableValueList": 0,
    "exclusiveProducer": 0,
    "canNotBeTakeItemFromCorpse": false,
    "manufacturableType": 0,
    "makeMaterial1": 502307,
    "makeMaterial2": 502201,
    "consumeCount": 1,
    "summonCode": 18,
    "restoreItemWhenResurrected": true
  },
  {
    "code": 502403,
    "name": "화염트랩",
    "modeType": 0,
    "itemType": "Special",
    "specialItemType": "Summon",
    "itemGrade": "Rare",
    "isCompletedItem": true,
    "markingType": "None",
    "craftAnimTrigger": "craftMetal",
    "stackable": 5,
    "initialCount": 1,
    "itemUsableType": "ALL",
    "itemUsableValueList": 0,
    "exclusiveProducer": 0,
    "canNotBeTakeItemFromCorpse": false,
    "manufacturableType": 0,
    "makeMaterial1": 502306,
    "makeMaterial2": 401202,
    "consumeCount": 1,
    "summonCode": 19,
    "restoreItemWhenResurrected": true
  },
  {
    "code": 502404,
    "name": "C4",
    "modeType": 0,
    "itemType": "Special",
    "specialItemType": "Summon",
    "itemGrade": "Epic",
    "isCompletedItem": true,
    "markingType": "None",
    "craftAnimTrigger": "craftMetal",
    "stackable": 5,
    "initialCount": 2,
    "itemUsableType": "ALL",
    "itemUsableValueList": 0,
    "exclusiveProducer": 0,
    "canNotBeTakeItemFromCorpse": false,
    "manufacturableType": 0,
    "makeMaterial1": 502307,
    "makeMaterial2": 401206,
    "consumeCount": 1,
    "summonCode": 20,
    "restoreItemWhenResurrected": true
  },
  {
    "code": 502405,
    "name": "더블기요틴",
    "modeType": 0,
    "itemType": "Special",
    "specialItemType": "Summon",
    "itemGrade": "Epic",
    "isCompletedItem": true,
    "markingType": "None",
    "craftAnimTrigger": "craftMetal",
    "stackable": 5,
    "initialCount": 1,
    "itemUsableType": "ALL",
    "itemUsableValueList": 0,
    "exclusiveProducer": 0,
    "canNotBeTakeItemFromCorpse": false,
    "manufacturableType": 0,
    "makeMaterial1": 502303,
    "makeMaterial2": 502305,
    "consumeCount": 1,
    "summonCode": 21,
    "restoreItemWhenResurrected": true
  },
  {
    "code": 502406,
    "name": "크레모어",
    "modeType": 0,
    "itemType": "Special",
    "specialItemType": "Summon",
    "itemGrade": "Epic",
    "isCompletedItem": true,
    "markingType": "None",
    "craftAnimTrigger": "craftMetal",
    "stackable": 5,
    "initialCount": 1,
    "itemUsableType": "ALL",
    "itemUsableValueList": 0,
    "exclusiveProducer": 0,
    "canNotBeTakeItemFromCorpse": false,
    "manufacturableType": 0,
    "makeMaterial1": 502304,
    "makeMaterial2": 502306,
    "consumeCount": 1,
    "summonCode": 22,
    "restoreItemWhenResurrected": true
  },
  {
    "code": 502407,
    "name": "히든메이든",
    "modeType": 0,
    "itemType": "Special",
    "specialItemType": "Summon",
    "itemGrade": "Rare",
    "isCompletedItem": true,
    "markingType": "None",
    "craftAnimTrigger": "craftMetal",
    "stackable": 5,
    "initialCount": 3,
    "itemUsableType": "ALL",
    "itemUsableValueList": 0,
    "exclusiveProducer": 0,
    "canNotBeTakeItemFromCorpse": false,
    "manufacturableType": 0,
    "makeMaterial1": 502202,
    "makeMaterial2": 502303,
    "consumeCount": 1,
    "summonCode": 23,
    "restoreItemWhenResurrected": true
  },
  {
    "code": 502501,
    "name": "리모트마인",
    "modeType": 0,
    "itemType": "Special",
    "specialItemType": "Summon",
    "itemGrade": "Legend",
    "isCompletedItem": true,
    "markingType": "None",
    "craftAnimTrigger": "craftMetal",
    "stackable": 5,
    "initialCount": 3,
    "itemUsableType": "ALL",
    "itemUsableValueList": 0,
    "exclusiveProducer": 0,
    "canNotBeTakeItemFromCorpse": false,
    "manufacturableType": 0,
    "makeMaterial1": 401403,
    "makeMaterial2": 502202,
    "consumeCount": 1,
    "summonCode": 24,
    "restoreItemWhenResurrected": true
  },
  {
    "code": 502502,
    "name": "스마트폭탄",
    "modeType": 0,
    "itemType": "Special",
    "specialItemType": "Summon",
    "itemGrade": "Legend",
    "isCompletedItem": true,
    "markingType": "None",
    "craftAnimTrigger": "craftMetal",
    "stackable": 5,
    "initialCount": 2,
    "itemUsableType": "ALL",
    "itemUsableValueList": 0,
    "exclusiveProducer": 0,
    "canNotBeTakeItemFromCorpse": false,
    "manufacturableType": 0,
    "makeMaterial1": 502307,
    "makeMaterial2": 501401,
    "consumeCount": 1,
    "summonCode": 25,
    "restoreItemWhenResurrected": true
  }
]