[
  {
    "code": 31,
    "nextUpgradecode": 32,
    "upgradeCredit": 0,
    "upgradeMaterial": 0,
    "skillCode": 4000001
  },
  {
    "code": 32,
    "nextUpgradecode": 0,
    "upgradeCredit": 0,
    "upgradeMaterial": 999999,
    "skillCode": 4000002
  },
  {
    "code": 41,
    "nextUpgradecode": 42,
    "upgradeCredit": 0,
    "upgradeMaterial": 0,
    "skillCode": 4001001
  },
  {
    "code": 42,
    "nextUpgradecode": 0,
    "upgradeCredit": 0,
    "upgradeMaterial": 999999,
    "skillCode": 4001002
  },
  {
    "code": 51,
    "nextUpgradecode": 52,
    "upgradeCredit": 0,
    "upgradeMaterial": 0,
    "skillCode": 4101001
  },
  {
    "code": 52,
    "nextUpgradecode": 0,
    "upgradeCredit": 0,
    "upgradeMaterial": 999999,
    "skillCode": 4101002
  },
  {
    "code": 61,
    "nextUpgradecode": 62,
    "upgradeCredit": 0,
    "upgradeMaterial": 0,
    "skillCode": 4102001
  },
  {
    "code": 62,
    "nextUpgradecode": 0,
    "upgradeCredit": 0,
    "upgradeMaterial": 999999,
    "skillCode": 4102002
  },
  {
    "code": 71,
    "nextUpgradecode": 72,
    "upgradeCredit": 0,
    "upgradeMaterial": 0,
    "skillCode": 4103001
  },
  {
    "code": 72,
    "nextUpgradecode": 0,
    "upgradeCredit": 0,
    "upgradeMaterial": 999999,
    "skillCode": 4103002
  },
  {
    "code": 81,
    "nextUpgradecode": 82,
    "upgradeCredit": 0,
    "upgradeMaterial": 0,
    "skillCode": 4104001
  },
  {
    "code": 82,
    "nextUpgradecode": 0,
    "upgradeCredit": 0,
    "upgradeMaterial": 999999,
    "skillCode": 4104002
  },
  {
    "code": 91,
    "nextUpgradecode": 92,
    "upgradeCredit": 0,
    "upgradeMaterial": 0,
    "skillCode": 4105001
  },
  {
    "code": 92,
    "nextUpgradecode": 0,
    "upgradeCredit": 0,
    "upgradeMaterial": 999999,
    "skillCode": 4105002
  },
  {
    "code": 111,
    "nextUpgradecode": 112,
    "upgradeCredit": 0,
    "upgradeMaterial": 0,
    "skillCode": 4107001
  },
  {
    "code": 112,
    "nextUpgradecode": 0,
    "upgradeCredit": 0,
    "upgradeMaterial": 999999,
    "skillCode": 4107002
  },
  {
    "code": 121,
    "nextUpgradecode": 122,
    "upgradeCredit": 0,
    "upgradeMaterial": 0,
    "skillCode": 4114001
  },
  {
    "code": 122,
    "nextUpgradecode": 0,
    "upgradeCredit": 0,
    "upgradeMaterial": 999999,
    "skillCode": 4114002
  },
  {
    "code": 131,
    "nextUpgradecode": 132,
    "upgradeCredit": 0,
    "upgradeMaterial": 0,
    "skillCode": 4112001
  },
  {
    "code": 132,
    "nextUpgradecode": 0,
    "upgradeCredit": 0,
    "upgradeMaterial": 999999,
    "skillCode": 4112002
  },
  {
    "code": 141,
    "nextUpgradecode": 142,
    "upgradeCredit": 0,
    "upgradeMaterial": 0,
    "skillCode": 4113001
  },
  {
    "code": 142,
    "nextUpgradecode": 0,
    "upgradeCredit": 0,
    "upgradeMaterial": 999999,
    "skillCode": 4113002
  },
  {
    "code": 151,
    "nextUpgradecode": 152,
    "upgradeCredit": 0,
    "upgradeMaterial": 0,
    "skillCode": 4108001
  },
  {
    "code": 152,
    "nextUpgradecode": 0,
    "upgradeCredit": 0,
    "upgradeMaterial": 999999,
    "skillCode": 4108002
  },
  {
    "code": 500011,
    "nextUpgradecode": 0,
    "upgradeCredit": 0,
    "upgradeMaterial": 0,
    "skillCode": 4501001
  },
  {
    "code": 500021,
    "nextUpgradecode": 0,
    "upgradeCredit": 0,
    "upgradeMaterial": 0,
    "skillCode": 4502001
  },
  {
    "code": 500031,
    "nextUpgradecode": 0,
    "upgradeCredit": 0,
    "upgradeMaterial": 0,
    "skillCode": 4503001
  },
  {
    "code": 500041,
    "nextUpgradecode": 0,
    "upgradeCredit": 0,
    "upgradeMaterial": 0,
    "skillCode": 4504001
  },
  {
    "code": 500051,
    "nextUpgradecode": 0,
    "upgradeCredit": 0,
    "upgradeMaterial": 0,
    "skillCode": 4505001
  },
  {
    "code": 500061,
    "nextUpgradecode": 0,
    "upgradeCredit": 0,
    "upgradeMaterial": 0,
    "skillCode": 4506001
  },
  {
    "code": 500071,
    "nextUpgradecode": 0,
    "upgradeCredit": 0,
    "upgradeMaterial": 0,
    "skillCode": 4507001
  },
  {
    "code": 500081,
    "nextUpgradecode": 0,
    "upgradeCredit": 0,
    "upgradeMaterial": 0,
    "skillCode": 4508001
  },
  {
    "code": 500091,
    "nextUpgradecode": 0,
    "upgradeCredit": 0,
    "upgradeMaterial": 0,
    "skillCode": 4509001
  },
  {
    "code": 500101,
    "nextUpgradecode": 0,
    "upgradeCredit": 0,
    "upgradeMaterial": 0,
    "skillCode": 4510001
  },
  {
    "code": 500111,
    "nextUpgradecode": 0,
    "upgradeCredit": 0,
    "upgradeMaterial": 0,
    "skillCode": 4511002
  },
  {
    "code": 500121,
    "nextUpgradecode": 500122,
    "upgradeCredit": 0,
    "upgradeMaterial": 0,
    "skillCode": 4512001
  },
  {
    "code": 500122,
    "nextUpgradecode": 0,
    "upgradeCredit": 0,
    "upgradeMaterial": 0,
    "skillCode": 4512002
  },
  {
    "code": 500131,
    "nextUpgradecode": 500132,
    "upgradeCredit": 0,
    "upgradeMaterial": 0,
    "skillCode": 4513001
  },
  {
    "code": 500132,
    "nextUpgradecode": 0,
    "upgradeCredit": 0,
    "upgradeMaterial": 0,
    "skillCode": 4513002
  },
  {
    "code": 500141,
    "nextUpgradecode": 500142,
    "upgradeCredit": 0,
    "upgradeMaterial": 0,
    "skillCode": 4514001
  },
  {
    "code": 500142,
    "nextUpgradecode": 0,
    "upgradeCredit": 0,
    "upgradeMaterial": 0,
    "skillCode": 4514002
  },
  {
    "code": 500151,
    "nextUpgradecode": 500152,
    "upgradeCredit": 0,
    "upgradeMaterial": 0,
    "skillCode": 4515001
  },
  {
    "code": 500152,
    "nextUpgradecode": 0,
    "upgradeCredit": 0,
    "upgradeMaterial": 0,
    "skillCode": 4515002
  },
  {
    "code": 500161,
    "nextUpgradecode": 500162,
    "upgradeCredit": 0,
    "upgradeMaterial": 0,
    "skillCode": 4516001
  },
  {
    "code": 500162,
    "nextUpgradecode": 0,
    "upgradeCredit": 0,
    "upgradeMaterial": 0,
    "skillCode": 4516002
  },
  {
    "code": 500171,
    "nextUpgradecode": 500172,
    "upgradeCredit": 0,
    "upgradeMaterial": 0,
    "skillCode": 4517001
  },
  {
    "code": 500172,
    "nextUpgradecode": 0,
    "upgradeCredit": 0,
    "upgradeMaterial": 0,
    "skillCode": 4517002
  },
  {
    "code": 500181,
    "nextUpgradecode": 500182,
    "upgradeCredit": 0,
    "upgradeMaterial": 0,
    "skillCode": 4518001
  },
  {
    "code": 500182,
    "nextUpgradecode": 0,
    "upgradeCredit": 0,
    "upgradeMaterial": 0,
    "skillCode": 4518002
  },
  {
    "code": 500191,
    "nextUpgradecode": 500192,
    "upgradeCredit": 0,
    "upgradeMaterial": 0,
    "skillCode": 4519001
  },
  {
    "code": 500192,
    "nextUpgradecode": 0,
    "upgradeCredit": 0,
    "upgradeMaterial": 0,
    "skillCode": 4519002
  },
  {
    "code": 500201,
    "nextUpgradecode": 500202,
    "upgradeCredit": 0,
    "upgradeMaterial": 0,
    "skillCode": 4523001
  },
  {
    "code": 500202,
    "nextUpgradecode": 0,
    "upgradeCredit": 0,
    "upgradeMaterial": 0,
    "skillCode": 4523002
  },
  {
    "code": 500211,
    "nextUpgradecode": 500212,
    "upgradeCredit": 0,
    "upgradeMaterial": 0,
    "skillCode": 4521001
  },
  {
    "code": 500212,
    "nextUpgradecode": 0,
    "upgradeCredit": 0,
    "upgradeMaterial": 0,
    "skillCode": 4521002
  },
  {
    "code": 500221,
    "nextUpgradecode": 500222,
    "upgradeCredit": 0,
    "upgradeMaterial": 0,
    "skillCode": 4522001
  },
  {
    "code": 500222,
    "nextUpgradecode": 0,
    "upgradeCredit": 0,
    "upgradeMaterial": 0,
    "skillCode": 4522002
  },
  {
    "code": 500231,
    "nextUpgradecode": 500232,
    "upgradeCredit": 0,
    "upgradeMaterial": 0,
    "skillCode": 4520001
  },
  {
    "code": 500232,
    "nextUpgradecode": 0,
    "upgradeCredit": 0,
    "upgradeMaterial": 0,
    "skillCode": 4520002
  },
  {
    "code": 1000001,
    "nextUpgradecode": 1000002,
    "upgradeCredit": 120,
    "upgradeMaterial": 0,
    "skillCode": 4999001
  },
  {
    "code": 1000002,
    "nextUpgradecode": 1000003,
    "upgradeCredit": 150,
    "upgradeMaterial": 0,
    "skillCode": 4999002
  },
  {
    "code": 1000003,
    "nextUpgradecode": 1000004,
    "upgradeCredit": 240,
    "upgradeMaterial": 0,
    "skillCode": 4999003
  },
  {
    "code": 1000004,
    "nextUpgradecode": 1000005,
    "upgradeCredit": 500,
    "upgradeMaterial": 0,
    "skillCode": 4999004
  },
  {
    "code": 1000005,
    "nextUpgradecode": 0,
    "upgradeCredit": 0,
    "upgradeMaterial": 999999,
    "skillCode": 4999005
  }
]